GG/GG.py
GG/__init__.py
GauInt-0.0.3.dist-info/LICENSE
GauInt-0.0.3.dist-info/METADATA
GauInt-0.0.3.dist-info/WHEEL
GauInt-0.0.3.dist-info/top_level.txt
GauInt-0.0.3.dist-info/RECORD
