Metadata-Version: 2.1
Name: GauInt
Version: 0.0.3
Summary: Gaussian integer x+iy and its prime factorization
Home-page: https://github.com/tt-nakamura/GG
Author: Takahiro Nakamura
Author-email: a41757@gmail.com
License: UNKNOWN
Project-URL: Bug Tracker, https://github.com/tt-nakamura/GG/issues
Platform: UNKNOWN
Classifier: Programming Language :: Python :: 3
Classifier: License :: OSI Approved :: MIT License
Classifier: Operating System :: OS Independent
Requires-Python: >=3.6
License-File: LICENSE
